{"paths": {"admin/js/vendor/select2/i18n/af.js": "admin/js/vendor/select2/i18n/af.4f6fcd73488c.js", "admin/js/vendor/select2/i18n/ar.js": "admin/js/vendor/select2/i18n/ar.65aa8e36bf5d.js", "admin/js/vendor/select2/i18n/az.js": "admin/js/vendor/select2/i18n/az.270c257daf81.js", "admin/js/vendor/select2/i18n/bg.js": "admin/js/vendor/select2/i18n/bg.39b8be30d4f0.js", "admin/js/vendor/select2/i18n/bn.js": "admin/js/vendor/select2/i18n/bn.6d42b4dd5665.js", "admin/js/vendor/select2/i18n/bs.js": "admin/js/vendor/select2/i18n/bs.91624382358e.js", "admin/js/vendor/select2/i18n/ca.js": "admin/js/vendor/select2/i18n/ca.a166b745933a.js", "admin/js/vendor/select2/i18n/cs.js": "admin/js/vendor/select2/i18n/cs.4f43e8e7d33a.js", "admin/js/vendor/select2/i18n/da.js": "admin/js/vendor/select2/i18n/da.766346afe4dd.js", "admin/js/vendor/select2/i18n/de.js": "admin/js/vendor/select2/i18n/de.8a1c222b0204.js", "admin/js/vendor/select2/i18n/dsb.js": "admin/js/vendor/select2/i18n/dsb.56372c92d2f1.js", "admin/js/vendor/select2/i18n/el.js": "admin/js/vendor/select2/i18n/el.27097f071856.js", "admin/js/vendor/select2/i18n/en.js": "admin/js/vendor/select2/i18n/en.cf932ba09a98.js", "admin/js/vendor/select2/i18n/es.js": "admin/js/vendor/select2/i18n/es.66dbc2652fb1.js", "admin/js/vendor/select2/i18n/et.js": "admin/js/vendor/select2/i18n/et.2b96fd98289d.js", "admin/js/vendor/select2/i18n/eu.js": "admin/js/vendor/select2/i18n/eu.adfe5c97b72c.js", "admin/js/vendor/select2/i18n/fa.js": "admin/js/vendor/select2/i18n/fa.3b5bd1961cfd.js", "admin/js/vendor/select2/i18n/fi.js": "admin/js/vendor/select2/i18n/fi.614ec42aa9ba.js", "admin/js/vendor/select2/i18n/fr.js": "admin/js/vendor/select2/i18n/fr.05e0542fcfe6.js", "admin/js/vendor/select2/i18n/gl.js": "admin/js/vendor/select2/i18n/gl.d99b1fedaa86.js", "admin/js/vendor/select2/i18n/he.js": "admin/js/vendor/select2/i18n/he.e420ff6cd3ed.js", "admin/js/vendor/select2/i18n/hi.js": "admin/js/vendor/select2/i18n/hi.70640d41628f.js", "admin/js/vendor/select2/i18n/hr.js": "admin/js/vendor/select2/i18n/hr.a2b092cc1147.js", "admin/js/vendor/select2/i18n/hsb.js": "admin/js/vendor/select2/i18n/hsb.fa3b55265efe.js", "admin/js/vendor/select2/i18n/hu.js": "admin/js/vendor/select2/i18n/hu.6ec6039cb8a3.js", "admin/js/vendor/select2/i18n/hy.js": "admin/js/vendor/select2/i18n/hy.c7babaeef5a6.js", "admin/js/vendor/select2/i18n/id.js": "admin/js/vendor/select2/i18n/id.04debded514d.js", "admin/js/vendor/select2/i18n/is.js": "admin/js/vendor/select2/i18n/is.3ddd9a6a97e9.js", "admin/js/vendor/select2/i18n/it.js": "admin/js/vendor/select2/i18n/it.be4fe8d365b5.js", "admin/js/vendor/select2/i18n/ja.js": "admin/js/vendor/select2/i18n/ja.170ae885d74f.js", "admin/js/vendor/select2/i18n/ka.js": "admin/js/vendor/select2/i18n/ka.2083264a54f0.js", "admin/js/vendor/select2/i18n/km.js": "admin/js/vendor/select2/i18n/km.c23089cb06ca.js", "admin/js/vendor/select2/i18n/ko.js": "admin/js/vendor/select2/i18n/ko.e7be6c20e673.js", "admin/js/vendor/select2/i18n/lt.js": "admin/js/vendor/select2/i18n/lt.23c7ce903300.js", "admin/js/vendor/select2/i18n/lv.js": "admin/js/vendor/select2/i18n/lv.08e62128eac1.js", "admin/js/vendor/select2/i18n/mk.js": "admin/js/vendor/select2/i18n/mk.dabbb9087130.js", "admin/js/vendor/select2/i18n/ms.js": "admin/js/vendor/select2/i18n/ms.4ba82c9a51ce.js", "admin/js/vendor/select2/i18n/nb.js": "admin/js/vendor/select2/i18n/nb.da2fce143f27.js", "admin/js/vendor/select2/i18n/ne.js": "admin/js/vendor/select2/i18n/ne.3d79fd3f08db.js", "admin/js/vendor/select2/i18n/nl.js": "admin/js/vendor/select2/i18n/nl.997868a37ed8.js", "admin/js/vendor/select2/i18n/pl.js": "admin/js/vendor/select2/i18n/pl.6031b4f16452.js", "admin/js/vendor/select2/i18n/ps.js": "admin/js/vendor/select2/i18n/ps.38dfa47af9e0.js", "admin/js/vendor/select2/i18n/pt-BR.js": "admin/js/vendor/select2/i18n/pt-BR.e1b294433e7f.js", "admin/js/vendor/select2/i18n/pt.js": "admin/js/vendor/select2/i18n/pt.33b4a3b44d43.js", "admin/js/vendor/select2/i18n/ro.js": "admin/js/vendor/select2/i18n/ro.f75cb460ec3b.js", "admin/js/vendor/select2/i18n/ru.js": "admin/js/vendor/select2/i18n/ru.934aa95f5b5f.js", "admin/js/vendor/select2/i18n/sk.js": "admin/js/vendor/select2/i18n/sk.33d02cef8d11.js", "admin/js/vendor/select2/i18n/sl.js": "admin/js/vendor/select2/i18n/sl.131a78bc0752.js", "admin/js/vendor/select2/i18n/sq.js": "admin/js/vendor/select2/i18n/sq.5636b60d29c9.js", "admin/js/vendor/select2/i18n/sr-Cyrl.js": "admin/js/vendor/select2/i18n/sr-Cyrl.f254bb8c4c7c.js", "admin/js/vendor/select2/i18n/sr.js": "admin/js/vendor/select2/i18n/sr.5ed85a48f483.js", "admin/js/vendor/select2/i18n/sv.js": "admin/js/vendor/select2/i18n/sv.7a9c2f71e777.js", "admin/js/vendor/select2/i18n/th.js": "admin/js/vendor/select2/i18n/th.f38c20b0221b.js", "admin/js/vendor/select2/i18n/tk.js": "admin/js/vendor/select2/i18n/tk.7c572a68c78f.js", "admin/js/vendor/select2/i18n/tr.js": "admin/js/vendor/select2/i18n/tr.b5a0643d1545.js", "admin/js/vendor/select2/i18n/uk.js": "admin/js/vendor/select2/i18n/uk.8cede7f4803c.js", "admin/js/vendor/select2/i18n/vi.js": "admin/js/vendor/select2/i18n/vi.097a5b75b3e1.js", "admin/js/vendor/select2/i18n/zh-CN.js": "admin/js/vendor/select2/i18n/zh-CN.2cff662ec5f9.js", "admin/js/vendor/select2/i18n/zh-TW.js": "admin/js/vendor/select2/i18n/zh-TW.04554a227c2b.js", "admin/css/vendor/select2/LICENSE-SELECT2.md": "admin\\css\\vendor\\select2\\LICENSE-SELECT2.f94142512c91.md", "admin/css/vendor/select2/select2.css": "admin/css/vendor/select2/select2.a2194c262648.css", "admin/css/vendor/select2/select2.min.css": "admin/css/vendor/select2/select2.min.9f54e6414f87.css", "admin/js/vendor/jquery/jquery.js": "admin/js/vendor/jquery/jquery.0208b96062ba.js", "admin/js/vendor/jquery/jquery.min.js": "admin/js/vendor/jquery/jquery.min.641dd1437010.js", "admin/js/vendor/jquery/LICENSE.txt": "admin\\js\\vendor\\jquery\\LICENSE.de877aa6d744.txt", "admin/js/vendor/select2/LICENSE.md": "admin\\js\\vendor\\select2\\LICENSE.f94142512c91.md", "admin/js/vendor/select2/select2.full.js": "admin/js/vendor/select2/select2.full.c2afdeda3058.js", "admin/js/vendor/select2/select2.full.min.js": "admin/js/vendor/select2/select2.full.min.fcd7500d8e13.js", "admin/js/vendor/xregexp/LICENSE.txt": "admin\\js\\vendor\\xregexp\\LICENSE.bf79e414957a.txt", "admin/js/vendor/xregexp/xregexp.js": "admin/js/vendor/xregexp/xregexp.efda034b9537.js", "admin/js/vendor/xregexp/xregexp.min.js": "admin/js/vendor/xregexp/xregexp.min.b0439563a5d3.js", "scss/bootstrap/scss/mixins/_alert.scss": "scss\\bootstrap\\scss\\mixins\\_alert.2bed73c51e64.scss", "scss/bootstrap/scss/mixins/_background-variant.scss": "scss\\bootstrap\\scss\\mixins\\_background-variant.c616ce854b35.scss", "scss/bootstrap/scss/mixins/_badge.scss": "scss\\bootstrap\\scss\\mixins\\_badge.9245d772f26f.scss", "scss/bootstrap/scss/mixins/_border-radius.scss": "scss\\bootstrap\\scss\\mixins\\_border-radius.b1fe7aa86dc0.scss", "scss/bootstrap/scss/mixins/_box-shadow.scss": "scss\\bootstrap\\scss\\mixins\\_box-shadow.e50901e86d7f.scss", "scss/bootstrap/scss/mixins/_breakpoints.scss": "scss\\bootstrap\\scss\\mixins\\_breakpoints.9a14819fe9ca.scss", "scss/bootstrap/scss/mixins/_buttons.scss": "scss\\bootstrap\\scss\\mixins\\_buttons.0d1d3c2ef8c4.scss", "scss/bootstrap/scss/mixins/_caret.scss": "scss\\bootstrap\\scss\\mixins\\_caret.fc2f3d41523c.scss", "scss/bootstrap/scss/mixins/_clearfix.scss": "scss\\bootstrap\\scss\\mixins\\_clearfix.f8d39651a105.scss", "scss/bootstrap/scss/mixins/_deprecate.scss": "scss\\bootstrap\\scss\\mixins\\_deprecate.198564417395.scss", "scss/bootstrap/scss/mixins/_float.scss": "scss\\bootstrap\\scss\\mixins\\_float.87899ae33449.scss", "scss/bootstrap/scss/mixins/_forms.scss": "scss\\bootstrap\\scss\\mixins\\_forms.876605cd4301.scss", "scss/bootstrap/scss/mixins/_gradients.scss": "scss\\bootstrap\\scss\\mixins\\_gradients.0f44c939a3f2.scss", "scss/bootstrap/scss/mixins/_grid-framework.scss": "scss\\bootstrap\\scss\\mixins\\_grid-framework.c4d47a361a3a.scss", "scss/bootstrap/scss/mixins/_grid.scss": "scss\\bootstrap\\scss\\mixins\\_grid.4c24effe7e71.scss", "scss/bootstrap/scss/mixins/_hover.scss": "scss\\bootstrap\\scss\\mixins\\_hover.60a4287f9d84.scss", "scss/bootstrap/scss/mixins/_image.scss": "scss\\bootstrap\\scss\\mixins\\_image.f450601fbd9a.scss", "scss/bootstrap/scss/mixins/_list-group.scss": "scss\\bootstrap\\scss\\mixins\\_list-group.d3000f3208a4.scss", "scss/bootstrap/scss/mixins/_lists.scss": "scss\\bootstrap\\scss\\mixins\\_lists.deb8df605dc4.scss", "scss/bootstrap/scss/mixins/_nav-divider.scss": "scss\\bootstrap\\scss\\mixins\\_nav-divider.24720d5c00af.scss", "scss/bootstrap/scss/mixins/_pagination.scss": "scss\\bootstrap\\scss\\mixins\\_pagination.89f0d99dff6d.scss", "scss/bootstrap/scss/mixins/_reset-text.scss": "scss\\bootstrap\\scss\\mixins\\_reset-text.1ddcdf93d8d2.scss", "scss/bootstrap/scss/mixins/_resize.scss": "scss\\bootstrap\\scss\\mixins\\_resize.af032cea5fd5.scss", "scss/bootstrap/scss/mixins/_screen-reader.scss": "scss\\bootstrap\\scss\\mixins\\_screen-reader.a669545a5de3.scss", "scss/bootstrap/scss/mixins/_size.scss": "scss\\bootstrap\\scss\\mixins\\_size.07e14cdbaee0.scss", "scss/bootstrap/scss/mixins/_table-row.scss": "scss\\bootstrap\\scss\\mixins\\_table-row.2fc9394e48aa.scss", "scss/bootstrap/scss/mixins/_text-emphasis.scss": "scss\\bootstrap\\scss\\mixins\\_text-emphasis.47485aaa1da5.scss", "scss/bootstrap/scss/mixins/_text-hide.scss": "scss\\bootstrap\\scss\\mixins\\_text-hide.31dc39c6f1ca.scss", "scss/bootstrap/scss/mixins/_text-truncate.scss": "scss\\bootstrap\\scss\\mixins\\_text-truncate.c51a1018bf42.scss", "scss/bootstrap/scss/mixins/_transition.scss": "scss\\bootstrap\\scss\\mixins\\_transition.c079e56eb3f2.scss", "scss/bootstrap/scss/mixins/_visibility.scss": "scss\\bootstrap\\scss\\mixins\\_visibility.3d3bc176127e.scss", "scss/bootstrap/scss/utilities/_align.scss": "scss\\bootstrap\\scss\\utilities\\_align.2d85a42f5904.scss", "scss/bootstrap/scss/utilities/_background.scss": "scss\\bootstrap\\scss\\utilities\\_background.73dbbd77bc94.scss", "scss/bootstrap/scss/utilities/_borders.scss": "scss\\bootstrap\\scss\\utilities\\_borders.14aedc8584c9.scss", "scss/bootstrap/scss/utilities/_clearfix.scss": "scss\\bootstrap\\scss\\utilities\\_clearfix.01ed6cc70519.scss", "scss/bootstrap/scss/utilities/_display.scss": "scss\\bootstrap\\scss\\utilities\\_display.8af96c91de4e.scss", "scss/bootstrap/scss/utilities/_embed.scss": "scss\\bootstrap\\scss\\utilities\\_embed.d3f25ca3432b.scss", "scss/bootstrap/scss/utilities/_flex.scss": "scss\\bootstrap\\scss\\utilities\\_flex.6a75ca706305.scss", "scss/bootstrap/scss/utilities/_float.scss": "scss\\bootstrap\\scss\\utilities\\_float.caa8e0a1ce2b.scss", "scss/bootstrap/scss/utilities/_interactions.scss": "scss\\bootstrap\\scss\\utilities\\_interactions.884dc3784244.scss", "scss/bootstrap/scss/utilities/_overflow.scss": "scss\\bootstrap\\scss\\utilities\\_overflow.db617c241dbc.scss", "scss/bootstrap/scss/utilities/_position.scss": "scss\\bootstrap\\scss\\utilities\\_position.0ca5a3796af5.scss", "scss/bootstrap/scss/utilities/_screenreaders.scss": "scss\\bootstrap\\scss\\utilities\\_screenreaders.84c388e27d90.scss", "scss/bootstrap/scss/utilities/_shadows.scss": "scss\\bootstrap\\scss\\utilities\\_shadows.8d38293481d0.scss", "scss/bootstrap/scss/utilities/_sizing.scss": "scss\\bootstrap\\scss\\utilities\\_sizing.3e7cdb7eadea.scss", "scss/bootstrap/scss/utilities/_spacing.scss": "scss\\bootstrap\\scss\\utilities\\_spacing.c401a7ad414b.scss", "scss/bootstrap/scss/utilities/_stretched-link.scss": "scss\\bootstrap\\scss\\utilities\\_stretched-link.26d1a1fb32d4.scss", "scss/bootstrap/scss/utilities/_text.scss": "scss\\bootstrap\\scss\\utilities\\_text.83111d83a3ba.scss", "scss/bootstrap/scss/utilities/_visibility.scss": "scss\\bootstrap\\scss\\utilities\\_visibility.545510f15dee.scss", "scss/bootstrap/scss/vendor/_rfs.scss": "scss\\bootstrap\\scss\\vendor\\_rfs.23ec02c88f8d.scss", "admin/img/gis/move_vertex_off.svg": "admin\\img\\gis\\move_vertex_off.7a23bf31ef8a.svg", "admin/img/gis/move_vertex_on.svg": "admin\\img\\gis\\move_vertex_on.0047eba25b67.svg", "admin/js/admin/DateTimeShortcuts.js": "admin/js/admin/DateTimeShortcuts.9f6e209cebca.js", "admin/js/admin/RelatedObjectLookups.js": "admin/js/admin/RelatedObjectLookups.8609f99b9ab2.js", "lib/owlcarousel/assets/ajax-loader.gif": "lib\\owlcarousel\\assets\\ajax-loader.01000918725a.gif", "lib/owlcarousel/assets/owl.carousel.css": "lib/owlcarousel/assets/owl.carousel.651995f1c0e4.css", "lib/owlcarousel/assets/owl.carousel.min.css": "lib/owlcarousel/assets/owl.carousel.min.496b027c8d74.css", "lib/owlcarousel/assets/owl.theme.default.css": "lib/owlcarousel/assets/owl.theme.default.26dd7ebd96f6.css", "lib/owlcarousel/assets/owl.theme.default.min.css": "lib/owlcarousel/assets/owl.theme.default.min.275048a23c69.css", "lib/owlcarousel/assets/owl.theme.green.css": "lib/owlcarousel/assets/owl.theme.green.8d78112daf15.css", "lib/owlcarousel/assets/owl.theme.green.min.css": "lib/owlcarousel/assets/owl.theme.green.min.95a767285dbb.css", "lib/owlcarousel/assets/owl.video.play.png": "lib\\owlcarousel\\assets\\owl.video.play.4a37f8008959.png", "scss/bootstrap/scss/bootstrap-grid.scss": "scss\\bootstrap\\scss\\bootstrap-grid.a7c672f5b566.scss", "scss/bootstrap/scss/bootstrap-reboot.scss": "scss\\bootstrap\\scss\\bootstrap-reboot.d7304df6a6ed.scss", "scss/bootstrap/scss/bootstrap.scss": "scss\\bootstrap\\scss\\bootstrap.e92971ad4397.scss", "scss/bootstrap/scss/_alert.scss": "scss\\bootstrap\\scss\\_alert.f3cea8d46257.scss", "scss/bootstrap/scss/_badge.scss": "scss\\bootstrap\\scss\\_badge.ce84cd07128b.scss", "scss/bootstrap/scss/_breadcrumb.scss": "scss\\bootstrap\\scss\\_breadcrumb.2a2195660bfe.scss", "scss/bootstrap/scss/_button-group.scss": "scss\\bootstrap\\scss\\_button-group.aa313e235a30.scss", "scss/bootstrap/scss/_buttons.scss": "scss\\bootstrap\\scss\\_buttons.a14555de3d65.scss", "scss/bootstrap/scss/_card.scss": "scss\\bootstrap\\scss\\_card.dca715a63a8b.scss", "scss/bootstrap/scss/_carousel.scss": "scss\\bootstrap\\scss\\_carousel.4eefd8781098.scss", "scss/bootstrap/scss/_close.scss": "scss\\bootstrap\\scss\\_close.51dbb3005747.scss", "scss/bootstrap/scss/_code.scss": "scss\\bootstrap\\scss\\_code.498c7818162f.scss", "scss/bootstrap/scss/_custom-forms.scss": "scss\\bootstrap\\scss\\_custom-forms.d6584b2a4215.scss", "scss/bootstrap/scss/_dropdown.scss": "scss\\bootstrap\\scss\\_dropdown.0d994065dab7.scss", "scss/bootstrap/scss/_forms.scss": "scss\\bootstrap\\scss\\_forms.231537fe2ae7.scss", "scss/bootstrap/scss/_functions.scss": "scss\\bootstrap\\scss\\_functions.5eccb78a39ab.scss", "scss/bootstrap/scss/_grid.scss": "scss\\bootstrap\\scss\\_grid.0737b1e79491.scss", "scss/bootstrap/scss/_images.scss": "scss\\bootstrap\\scss\\_images.d50c4811e230.scss", "scss/bootstrap/scss/_input-group.scss": "scss\\bootstrap\\scss\\_input-group.a0e7ae2c4209.scss", "scss/bootstrap/scss/_jumbotron.scss": "scss\\bootstrap\\scss\\_jumbotron.d969f3ff6b93.scss", "scss/bootstrap/scss/_list-group.scss": "scss\\bootstrap\\scss\\_list-group.0d46407205e4.scss", "scss/bootstrap/scss/_media.scss": "scss\\bootstrap\\scss\\_media.d2ea169e5ccb.scss", "scss/bootstrap/scss/_mixins.scss": "scss\\bootstrap\\scss\\_mixins.3123d0b4c5fe.scss", "scss/bootstrap/scss/_modal.scss": "scss\\bootstrap\\scss\\_modal.a49750633d29.scss", "scss/bootstrap/scss/_nav.scss": "scss\\bootstrap\\scss\\_nav.025aff18f045.scss", "scss/bootstrap/scss/_navbar.scss": "scss\\bootstrap\\scss\\_navbar.8ad41716fbcf.scss", "scss/bootstrap/scss/_pagination.scss": "scss\\bootstrap\\scss\\_pagination.d361942f4f07.scss", "scss/bootstrap/scss/_popover.scss": "scss\\bootstrap\\scss\\_popover.6758af26108d.scss", "scss/bootstrap/scss/_print.scss": "scss\\bootstrap\\scss\\_print.02c5f9cef09b.scss", "scss/bootstrap/scss/_progress.scss": "scss\\bootstrap\\scss\\_progress.49e53429e377.scss", "scss/bootstrap/scss/_reboot.scss": "scss\\bootstrap\\scss\\_reboot.7def88d1b971.scss", "scss/bootstrap/scss/_root.scss": "scss\\bootstrap\\scss\\_root.10c061bb2595.scss", "scss/bootstrap/scss/_spinners.scss": "scss\\bootstrap\\scss\\_spinners.4d1e8876dbaa.scss", "scss/bootstrap/scss/_tables.scss": "scss\\bootstrap\\scss\\_tables.ec7f2a3120db.scss", "scss/bootstrap/scss/_toasts.scss": "scss\\bootstrap\\scss\\_toasts.e41c135b1135.scss", "scss/bootstrap/scss/_tooltip.scss": "scss\\bootstrap\\scss\\_tooltip.61cfa44c3bbc.scss", "scss/bootstrap/scss/_transitions.scss": "scss\\bootstrap\\scss\\_transitions.3718dbf96921.scss", "scss/bootstrap/scss/_type.scss": "scss\\bootstrap\\scss\\_type.606bf8337b2f.scss", "scss/bootstrap/scss/_utilities.scss": "scss\\bootstrap\\scss\\_utilities.413e7a2eee66.scss", "scss/bootstrap/scss/_variables.scss": "scss\\bootstrap\\scss\\_variables.cbc805dc3154.scss", "admin/css/autocomplete.css": "admin/css/autocomplete.4a81fc4242d0.css", "admin/css/base.css": "admin/css/base.64976e0f7339.css", "admin/css/changelists.css": "admin/css/changelists.9237a1ac391b.css", "admin/css/dark_mode.css": "admin/css/dark_mode.ef27a31af300.css", "admin/css/dashboard.css": "admin/css/dashboard.e90f2068217b.css", "admin/css/forms.css": "admin/css/forms.3b181cba6653.css", "admin/css/login.css": "admin/css/login.586129c60a93.css", "admin/css/nav_sidebar.css": "admin/css/nav_sidebar.269a1bd44627.css", "admin/css/responsive.css": "admin/css/responsive.107cd2690311.css", "admin/css/responsive_rtl.css": "admin/css/responsive_rtl.97b066429fd8.css", "admin/css/rtl.css": "admin/css/rtl.4685390ad96d.css", "admin/css/widgets.css": "admin/css/widgets.0a3765e806b3.css", "admin/img/calendar-icons.svg": "admin\\img\\calendar-icons.39b290681a8b.svg", "admin/img/icon-addlink.svg": "admin\\img\\icon-addlink.d519b3bab011.svg", "admin/img/icon-alert.svg": "admin\\img\\icon-alert.034cc7d8a67f.svg", "admin/img/icon-calendar.svg": "admin\\img\\icon-calendar.ac7aea671bea.svg", "admin/img/icon-changelink.svg": "admin\\img\\icon-changelink.18d2fd706348.svg", "admin/img/icon-clock.svg": "admin\\img\\icon-clock.e1d4dfac3f2b.svg", "admin/img/icon-deletelink.svg": "admin\\img\\icon-deletelink.564ef9dc3854.svg", "admin/img/icon-no.svg": "admin\\img\\icon-no.439e821418cd.svg", "admin/img/icon-unknown-alt.svg": "admin\\img\\icon-unknown-alt.81536e128bb6.svg", "admin/img/icon-unknown.svg": "admin\\img\\icon-unknown.a18cb4398978.svg", "admin/img/icon-viewlink.svg": "admin\\img\\icon-viewlink.41eb31f7826e.svg", "admin/img/icon-yes.svg": "admin\\img\\icon-yes.d2f9f035226a.svg", "admin/img/inline-delete.svg": "admin\\img\\inline-delete.fec1b761f254.svg", "admin/img/LICENSE": "admin\\img\\LICENSE.2c54f4e1ca1c", "admin/img/README.txt": "admin\\img\\README.a70711a38d87.txt", "admin/img/search.svg": "admin\\img\\search.7cf54ff789c6.svg", "admin/img/selector-icons.svg": "admin\\img\\selector-icons.b4555096cea2.svg", "admin/img/sorting-icons.svg": "admin\\img\\sorting-icons.3a097b59f104.svg", "admin/img/tooltag-add.svg": "admin\\img\\tooltag-add.e59d620a9742.svg", "admin/img/tooltag-arrowright.svg": "admin\\img\\tooltag-arrowright.bbfb788a849e.svg", "admin/js/actions.js": "admin/js/actions.eac7e3441574.js", "admin/js/autocomplete.js": "admin/js/autocomplete.01591ab27be7.js", "admin/js/calendar.js": "admin/js/calendar.f8a5d055eb33.js", "admin/js/cancel.js": "admin/js/cancel.ecc4c5ca7b32.js", "admin/js/change_form.js": "admin/js/change_form.9d8ca4f96b75.js", "admin/js/collapse.js": "admin/js/collapse.f84e7410290f.js", "admin/js/core.js": "admin/js/core.cf103cd04ebf.js", "admin/js/filters.js": "admin/js/filters.0e360b7a9f80.js", "admin/js/inlines.js": "admin/js/inlines.22d4d93c00b4.js", "admin/js/jquery.init.js": "admin/js/jquery.init.b7781a0897fc.js", "admin/js/nav_sidebar.js": "admin/js/nav_sidebar.3b9190d420b1.js", "admin/js/popup_response.js": "admin/js/popup_response.c6cc78ea5551.js", "admin/js/prepopulate.js": "admin/js/prepopulate.bd2361dfd64d.js", "admin/js/prepopulate_init.js": "admin/js/prepopulate_init.6cac7f3105b8.js", "admin/js/SelectBox.js": "admin/js/SelectBox.7d3ce5a98007.js", "admin/js/SelectFilter2.js": "admin/js/SelectFilter2.bdb8d0cc579e.js", "admin/js/theme.js": "admin/js/theme.ab270f56bb9c.js", "admin/js/urlify.js": "admin/js/urlify.ae970a820212.js", "lib/easing/easing.js": "lib/easing/easing.ec0a5208d6fa.js", "lib/easing/easing.min.js": "lib/easing/easing.min.d64116a74288.js", "lib/owlcarousel/LICENSE": "lib\\owlcarousel\\LICENSE.35dd9820e346", "lib/owlcarousel/owl.carousel.js": "lib/owlcarousel/owl.carousel.0aa8dbbc9bec.js", "lib/owlcarousel/owl.carousel.min.js": "lib/owlcarousel/owl.carousel.min.b7b9c97cd68e.js", "css/style.css": "css/style.0183c4056884.css", "css/style.min.css": "css/style.min.d00ce2f21faf.css", "img/ads-700x70.jpg": "img\\ads-700x70.f0c0495f96b2.jpg", "img/cat-500x80-1.jpg": "img\\cat-500x80-1.ca35353fc1a2.jpg", "img/cat-500x80-2.jpg": "img\\cat-500x80-2.8fefbf656e58.jpg", "img/cat-500x80-3.jpg": "img\\cat-500x80-3.1452a1a3efd9.jpg", "img/cat-500x80-4.jpg": "img\\cat-500x80-4.930ea1eb1ff1.jpg", "img/header.jpg": "img\\header.d41d8cd98f00.jpg", "img/news-100x100-1.jpg": "img\\news-100x100-1.43b0a2fa0ae4.jpg", "img/news-100x100-2.jpg": "img\\news-100x100-2.93fac5387e26.jpg", "img/news-100x100-3.jpg": "img\\news-100x100-3.632820191d96.jpg", "img/news-100x100-4.jpg": "img\\news-100x100-4.913aaf81a01f.jpg", "img/news-100x100-5.jpg": "img\\news-100x100-5.06654e4b8e0b.jpg", "img/news-300x300-1.jpg": "img\\news-300x300-1.a217f170604b.jpg", "img/news-300x300-2.jpg": "img\\news-300x300-2.0204f3901a9d.jpg", "img/news-300x300-3.jpg": "img\\news-300x300-3.86a0b8322e9d.jpg", "img/news-300x300-4.jpg": "img\\news-300x300-4.246250c3ed52.jpg", "img/news-300x300-5.jpg": "img\\news-300x300-5.ed653a7564cc.jpg", "img/news-500x280-1.jpg": "img\\news-500x280-1.a6360a536146.jpg", "img/news-500x280-2.jpg": "img\\news-500x280-2.34cdc7819f0b.jpg", "img/news-500x280-3.jpg": "img\\news-500x280-3.331a15dd66ac.jpg", "img/news-500x280-4.jpg": "img\\news-500x280-4.f0e2d28a2973.jpg", "img/news-500x280-5.jpg": "img\\news-500x280-5.e9cb1e6f0402.jpg", "img/news-500x280-6.jpg": "img\\news-500x280-6.530efea23580.jpg", "img/news-700x435-1.jpg": "img\\news-700x435-1.f896adac6092.jpg", "img/news-700x435-2.jpg": "img\\news-700x435-2.78e139fab5a3.jpg", "img/news-80x80-1.jpg": "img\\news-80x80-1.97e74ead433e.jpg", "img/news-80x80-2.jpg": "img\\news-80x80-2.ca8b1555ef40.jpg", "img/news-80x80-3.jpg": "img\\news-80x80-3.bd5eca167f99.jpg", "img/news-80x80-4.jpg": "img\\news-80x80-4.c808355cbf64.jpg", "img/user.jpg": "img\\user.3b6a6290110a.jpg", "img/user.png": "img\\user.a474debf5766.png", "js/infinite.min.js": "js/infinite.min.a9e9aa085994.js", "js/jquery-3.1.1.min.js": "js/jquery-3.1.1.min.e071abda8fe6.js", "js/jquery.waypoints.min.js": "js/jquery.waypoints.min.7d05f92297de.js", "js/main.js": "js/main.3ba0932201c2.js", "mail/contact.js": "mail/contact.b3c4cf3e4b87.js", "mail/contact.php": "mail\\contact.adabe70b6cda.php", "mail/jqBootstrapValidation.min.js": "mail/jqBootstrapValidation.min.973855bb100d.js", "scss/style.scss": "scss\\style.70085157df9c.scss"}, "version": "1.1", "hash": "e6c646810dfa"}